[
  {
    "rank": "1",
    "player": "Cristiano Ronaldo",
    "nation": "Portugal",
    "international_goals": "143",
    "international_matches": "226"
  },
  {
    "rank": "2",
    "player": "Lionel Messi",
    "nation": "Argentina",
    "international_goals": "116",
    "international_matches": "198"
  },
  {
    "rank": "3",
    "player": "Bader Al-Mutawa",
    "nation": "Kuwait",
    "international_goals": "56",
    "international_matches": "196"
  },
  {
    "rank": "4",
    "player": "Luka Modrić",
    "nation": "Croatia",
    "international_goals": "28",
    "international_matches": "196"
  },
  {
    "rank": "5",
    "player": "Chin Ann Soh",
    "nation": "Malaysia",
    "international_goals": "13",
    "international_matches": "195"
  },
  {
    "rank": "6",
    "player": "Ahmed Kano",
    "nation": "Oman",
    "international_goals": "21",
    "international_matches": "186"
  },
  {
    "rank": "7",
    "player": "Ahmed Hassan",
    "nation": "Egypt",
    "international_goals": "33",
    "international_matches": "184"
  },
  {
    "rank": "8",
    "player": "Andrés Guardado",
    "nation": "Mexico",
    "international_goals": "28",
    "international_matches": "182"
  },
  {
    "rank": "9",
    "player": "Maynor Figueroa",
    "nation": "Honduras",
    "international_goals": "5",
    "international_matches": "181"
  },
  {
    "rank": "10",
    "player": "Sergio Ramos",
    "nation": "Spain",
    "international_goals": "23",
    "international_matches": "180"
  },
  {
    "rank": "11",
    "player": "Mohammad Al-Deayea",
    "nation": "Saudi Arabia",
    "international_goals": "-",
    "international_matches": "178"
  },
  {
    "rank": "12",
    "player": "Claudio Suárez",
    "nation": "Mexico",
    "international_goals": "6",
    "international_matches": "177"
  },
  {
    "rank": "13",
    "player": "Hossam Hassan",
    "nation": "Egypt",
    "international_goals": "68",
    "international_matches": "176"
  },
  {
    "rank": "14",
    "player": "Gianluigi Buffon",
    "nation": "Italy",
    "international_goals": "-",
    "international_matches": "176"
  },
  {
    "rank": "15",
    "player": "Amer Shafi",
    "nation": "Jordan",
    "international_goals": "1",
    "international_matches": "171"
  },
  {
    "rank": "16",
    "player": "Alexis Sánchez",
    "nation": "Chile",
    "international_goals": "51",
    "international_matches": "168"
  },
  {
    "rank": "17",
    "player": "Vitalijs Astafjevs",
    "nation": "Latvia",
    "international_goals": "16",
    "international_matches": "168"
  },
  {
    "rank": "18",
    "player": "Iván Hurtado",
    "nation": "Ecuador",
    "international_goals": "5",
    "international_matches": "168"
  },
  {
    "rank": "19",
    "player": "Iker Casillas",
    "nation": "Spain",
    "international_goals": "-",
    "international_matches": "167"
  },
  {
    "rank": "20",
    "player": "Robert Lewandowski",
    "nation": "Poland",
    "international_goals": "89",
    "international_matches": "166"
  },
  {
    "rank": "21",
    "player": "Hasan Al-Haydos",
    "nation": "Qatar",
    "international_goals": "39",
    "international_matches": "166"
  },
  {
    "rank": "22",
    "player": "Adnan Al-Talyani",
    "nation": "UAE",
    "international_goals": "53",
    "international_matches": "164"
  },
  {
    "rank": "23",
    "player": "Celso Borges",
    "nation": "Costa Rica",
    "international_goals": "27",
    "international_matches": "164"
  },
  {
    "rank": "24",
    "player": "Cobi Jones",
    "nation": "USA",
    "international_goals": "15",
    "international_matches": "164"
  },
  {
    "rank": "25",
    "player": "Sami Al-Jaber",
    "nation": "Saudi Arabia",
    "international_goals": "44",
    "international_matches": "163"
  }
]